{
  "parent": "minecraft:recipes/root",
  "criteria": {
    "has_azure_bluet_crate": {
      "conditions": {
        "items": [
          {
            "items": [
              "hoarding:azure_bluet_crate"
            ]
          }
        ]
      },
      "trigger": "minecraft:inventory_changed"
    },
    "has_the_recipe": {
      "conditions": {
        "recipe": "hoarding:decompress/azure_bluet"
      },
      "trigger": "minecraft:recipe_unlocked"
    }
  },
  "requirements": [
    [
      "has_azure_bluet_crate",
      "has_the_recipe"
    ]
  ],
  "rewards": {
    "recipes": [
      "hoarding:decompress/azure_bluet"
    ]
  },
  "sends_telemetry_event": false
}