{
  "parent": "minecraft:recipes/root",
  "criteria": {
    "has_cornflower": {
      "conditions": {
        "items": [
          {
            "items": [
              "minecraft:cornflower"
            ]
          }
        ]
      },
      "trigger": "minecraft:inventory_changed"
    },
    "has_the_recipe": {
      "conditions": {
        "recipe": "hoarding:compress/cornflower_crate"
      },
      "trigger": "minecraft:recipe_unlocked"
    }
  },
  "requirements": [
    [
      "has_cornflower",
      "has_the_recipe"
    ]
  ],
  "rewards": {
    "recipes": [
      "hoarding:compress/cornflower_crate"
    ]
  },
  "sends_telemetry_event": false
}